README.md
setup.cfg
setup.py
scrapy_botproxy/__init__.py
scrapy_botproxy.egg-info/PKG-INFO
scrapy_botproxy.egg-info/SOURCES.txt
scrapy_botproxy.egg-info/dependency_links.txt
scrapy_botproxy.egg-info/requires.txt
scrapy_botproxy.egg-info/top_level.txt