Metadata-Version: 1.1
Name: scrapy-botproxy
Version: 1.0.1
Summary: BotProxy (IP Rotating HTTP proxy) downloader middlewarefor Scrapy
Home-page: https://github.com/botproxy/scrapy-botproxy
Author: botproxy
Author-email: support@botproxy.net
License: MIT
Platform: UNKNOWN
Classifier: Framework :: Scrapy
Classifier: Development Status :: 5 - Production/Stable
Classifier: Environment :: Plugins
Classifier: Intended Audience :: Developers
Classifier: License :: OSI Approved :: MIT License
Classifier: Operating System :: OS Independent
Classifier: Programming Language :: Python
Classifier: Programming Language :: Python :: 2
Classifier: Programming Language :: Python :: 2.7
Classifier: Programming Language :: Python :: 3
Classifier: Programming Language :: Python :: 3.3
Classifier: Programming Language :: Python :: 3.4
Classifier: Programming Language :: Python :: 3.5
Classifier: Programming Language :: Python :: 3.6
Classifier: Topic :: Internet :: WWW/HTTP
Classifier: Topic :: Software Development :: Libraries :: Python Modules
